pyavanza/__init__.py
pyavanza/py.typed
pyavanza-0.7.1.dist-info/LICENSE
pyavanza-0.7.1.dist-info/METADATA
pyavanza-0.7.1.dist-info/WHEEL
pyavanza-0.7.1.dist-info/top_level.txt
pyavanza-0.7.1.dist-info/RECORD
